circ_spider/SpiderUtils.py
circ_spider/__init__.py
circ_spider/captcha_utils.py
circ_circ_spider-1.0.0.dist-info/LICENSE
circ_circ_spider-1.0.0.dist-info/METADATA
circ_circ_spider-1.0.0.dist-info/WHEEL
circ_circ_spider-1.0.0.dist-info/top_level.txt
circ_circ_spider-1.0.0.dist-info/RECORD
